cosma_backend/__init__.py
cosma_backend/__main__.py
cosma_backend/api/__init__.py
cosma_backend/api/files.py
cosma_backend/api/index.py
cosma_backend/api/models.py
cosma_backend/api/search.py
cosma_backend/api/status.py
cosma_backend/api/updates.py
cosma_backend/api/watch.py
cosma_backend/app.py
cosma_backend/db/__init__.py
cosma_backend/db/database.py
cosma_backend/discoverer/__init__.py
cosma_backend/discoverer/discoverer.py
cosma_backend/embedder/__init__.py
cosma_backend/embedder/embedder.py
cosma_backend/logging.py
cosma_backend/models/__init__.py
cosma_backend/models/file.py
cosma_backend/models/status.py
cosma_backend/models/update.py
cosma_backend/models/watch.py
cosma_backend/parser/__init__.py
cosma_backend/parser/media.py
cosma_backend/parser/parser.py
cosma_backend/parser/spotlight.py
cosma_backend/pipeline/__init__.py
cosma_backend/pipeline/pipeline.py
cosma_backend/schema.sql
cosma_backend/searcher/__init__.py
cosma_backend/searcher/searcher.py
cosma_backend/summarizer/__init__.py
cosma_backend/summarizer/summarizer.py
cosma_backend/utils/bundled.py
cosma_backend/utils/decorators.py
cosma_backend/utils/pubsub.py
cosma_backend/utils/sse.py
cosma_backend/watcher/__init__.py
cosma_backend/watcher/awatchdog.py
cosma_backend/watcher/watcher.py
cosma_backend-0.3.0.dist-info/WHEEL
cosma_backend-0.3.0.dist-info/METADATA
cosma_backend-0.3.0.dist-info/RECORD
