Metadata-Version: 2.3
Name: cosma-backend
Version: 0.3.0
Summary: Cosma backend
Requires-Dist: asqlite>=2.0.0
Requires-Dist: litellm>=1.77.5
Requires-Dist: markitdown[docx,pdf,pptx]>=0.1.3
Requires-Dist: ollama>=0.6.0
Requires-Dist: platformdirs>=4.5.0
Requires-Dist: quart>=0.20.0
Requires-Dist: quart-schema>=0.22.0
Requires-Dist: rich>=14.2.0
Requires-Dist: sentence-transformers>=5.1.1
Requires-Dist: sqlite-vec>=0.1.6
Requires-Dist: tiktoken>=0.11.0
Requires-Dist: uvicorn>=0.38.0
Requires-Dist: watchdog>=6.0.0
Requires-Dist: llama-cpp-python ; extra == 'llamacpp'
Requires-Python: >=3.12
Provides-Extra: llamacpp
